zentables/__init__.py
zentables/templates/prettyhtml.tpl
zentables/zentables.py
zentables-0.2.4.dist-info/LICENSE.md
zentables-0.2.4.dist-info/WHEEL
zentables-0.2.4.dist-info/METADATA
zentables-0.2.4.dist-info/RECORD
