Metadata-Version: 2.1
Name: zentables
Version: 0.2.4
Summary: Stress-free descriptive tables in Python.
Home-page: https://github.com/thepolicylab/ZenTables.git
License: MIT
Keywords: pandas,tables,display,styler
Author: Paul Xu
Author-email: yang_xu@brown.edu
Requires-Python: >=3.8,<4.0.0
Classifier: Development Status :: 4 - Beta
Classifier: Intended Audience :: Science/Research
Classifier: License :: OSI Approved :: MIT License
Classifier: Programming Language :: Python :: 3
Classifier: Programming Language :: Python :: 3.10
Classifier: Programming Language :: Python :: 3.8
Classifier: Programming Language :: Python :: 3.9
Classifier: Topic :: Scientific/Engineering
Requires-Dist: Jinja2 (>=3.0.1,<4.0.0)
Requires-Dist: click (>=8.1.3,<9.0.0)
Requires-Dist: pandas (>=1.4.0,<2.0.0)
Project-URL: Repository, https://github.com/thepolicylab/ZenTables.git
